MANIFEST.in
setup.py
bin/lwp
lwp/__init__.py
lwp.egg-info/PKG-INFO
lwp.egg-info/SOURCES.txt
lwp.egg-info/dependency_links.txt
lwp.egg-info/not-zip-safe
lwp.egg-info/requires.txt
lwp.egg-info/top_level.txt
lwp/app/__init__.py
lwp/app/views.py
lwp/lxc/__init__.py
lwp/lxclite/__init__.py
lwp/static/css/bootstrap-responsive.min.css
lwp/static/css/bootstrap-select.min.css
lwp/static/css/bootstrap.css
lwp/static/css/bootstrapSwitch.css
lwp/static/ico/favicon.ico
lwp/static/img/glyphicons-halflings-white.png
lwp/static/img/glyphicons-halflings.png
lwp/static/js/bootstrap.min.js
lwp/static/js/bootstrapSwitch.js
lwp/static/js/html5slider.js
lwp/static/js/jqBootstrapValidation.js
lwp/templates/about.html
lwp/templates/checkconfig.html
lwp/templates/edit.html
lwp/templates/index.html
lwp/templates/layout.html
lwp/templates/login.html
lwp/templates/lxc-net.html
lwp/templates/users.html
lwp/templates/includes/aside.html
lwp/templates/includes/modal_clone.html
lwp/templates/includes/modal_create.html
lwp/templates/includes/modal_delete.html
lwp/templates/includes/modal_destroy.html
lwp/templates/includes/modal_new_user.html
lwp/templates/includes/modal_reboot.html
lwp/templates/includes/modals.html
lwp/templates/includes/nav.html
resources/lwp.db