Metadata-Version: 1.1
Name: lwp
Version: 0.2-pre4
Summary: LXC Web Interface
Home-page: UNKNOWN
Author: Élie Deloumeau, Antoine Tanzilli
Author-email: UNKNOWN
License: MIT
Platform: linux
Classifier: Environment :: Console
Classifier: Programming Language :: Python
